<annotation verified="no"><folder>images</folder><filename>crop_1_crop_0_3277-compressed</filename><path>/home/badhon/Documents/thesis/dataset_sampled/wheat/usask_1/images/crop_1_crop_0_3277-compressed.png</path><source><database>Unknown</database></source><size><width>1024</width><height>1024</height><depth>3</depth></size><segmented>0</segmented><object><type>robndbox</type><name>wheat_head</name><pose>Unspecified</pose><truncated>0</truncated><difficult>0</difficult><robndbox><cx>513.5</cx><cy>928.0</cy><w>72.0</w><h>71.0</h><angle>1.570796</angle></robndbox></object><object><type>robndbox</type><name>wheat_head</name><pose>Unspecified</pose><truncated>0</truncated><difficult>0</difficult><robndbox><cx>582.0</cx><cy>961.5</cy><w>88.0</w><h>49.0</h><angle>0.0</angle></robndbox></object><object><type>robndbox</type><name>wheat_head</name><pose>Unspecified</pose><truncated>0</truncated><difficult>0</difficult><robndbox><cx>85.0</cx><cy>118.5</cy><w>170.0</w><h>121.0</h><angle>0.0</angle></robndbox></object><object><type>robndbox</type><name>wheat_head</name><pose>Unspecified</pose><truncated>0</truncated><difficult>0</difficult><robndbox><cx>529.0</cx><cy>848.0</cy><w>82.0</w><h>62.0</h><angle>0.0</angle></robndbox></object><object><type>robndbox</type><name>wheat_head</name><pose>Unspecified</pose><truncated>0</truncated><difficult>0</difficult><robndbox><cx>984.0</cx><cy>440.5</cy><w>147.0</w><h>78.0</h><angle>1.570796</angle></robndbox></object><object><type>robndbox</type><name>wheat_head</name><pose>Unspecified</pose><truncated>0</truncated><difficult>0</difficult><robndbox><cx>297.5</cx><cy>191.5</cy><w>157.0</w><h>89.0</h><angle>1.570796</angle></robndbox></object><object><type>robndbox</type><name>wheat_head</name><pose>Unspecified</pose><truncated>0</truncated><difficult>0</difficult><robndbox><cx>925.5</cx><cy>694.5</cy><w>99.0</w><h>85.0</h><angle>1.570796</angle></robndbox></object><object><type>robndbox</type><name>wheat_head</name><pose>Unspecified</pose><truncated>0</truncated><difficult>0</difficult><robndbox><cx>334.5</cx><cy>169.0</cy><w>136.0</w><h>105.0</h><angle>1.570796</angle></robndbox></object><object><type>robndbox</type><name>wheat_head</name><pose>Unspecified</pose><truncated>0</truncated><difficult>0</difficult><robndbox><cx>132.0</cx><cy>253.0</cy><w>96.0</w><h>90.0</h><angle>1.570796</angle></robndbox></object><object><type>robndbox</type><name>wheat_head</name><pose>Unspecified</pose><truncated>0</truncated><difficult>0</difficult><robndbox><cx>638.5</cx><cy>858.5</cy><w>99.0</w><h>95.0</h><angle>0.0</angle></robndbox></object><object><type>robndbox</type><name>wheat_head</name><pose>Unspecified</pose><truncated>0</truncated><difficult>0</difficult><robndbox><cx>990.0</cx><cy>333.0</cy><w>106.0</w><h>68.0</h><angle>1.570796</angle></robndbox></object><object><type>robndbox</type><name>wheat_head</name><pose>Unspecified</pose><truncated>0</truncated><difficult>0</difficult><robndbox><cx>610.0</cx><cy>192.5</cy><w>103.0</w><h>100.0</h><angle>1.570796</angle></robndbox></object><object><type>robndbox</type><name>wheat_head</name><pose>Unspecified</pose><truncated>0</truncated><difficult>0</difficult><robndbox><cx>593.5</cx><cy>105.0</cy><w>163.0</w><h>96.0</h><angle>0.0</angle></robndbox></object><object><type>robndbox</type><name>wheat_head</name><pose>Unspecified</pose><truncated>0</truncated><difficult>0</difficult><robndbox><cx>109.0</cx><cy>116.5</cy><w>136.0</w><h>117.0</h><angle>0.0</angle></robndbox></object><object><type>robndbox</type><name>wheat_head</name><pose>Unspecified</pose><truncated>0</truncated><difficult>0</difficult><robndbox><cx>997.0</cx><cy>763.0</cy><w>90.0</w><h>54.0</h><angle>1.570796</angle></robndbox></object><object><type>robndbox</type><name>wheat_head</name><pose>Unspecified</pose><truncated>0</truncated><difficult>0</difficult><robndbox><cx>802.0</cx><cy>664.0</cy><w>130.0</w><h>96.0</h><angle>1.570796</angle></robndbox></object><object><type>robndbox</type><name>wheat_head</name><pose>Unspecified</pose><truncated>0</truncated><difficult>0</difficult><robndbox><cx>933.5</cx><cy>190.5</cy><w>113.0</w><h>109.0</h><angle>1.570796</angle></robndbox></object><object><type>robndbox</type><name>wheat_head</name><pose>Unspecified</pose><truncated>0</truncated><difficult>0</difficult><robndbox><cx>177.0</cx><cy>22.5</cy><w>88.0</w><h>45.0</h><angle>0.0</angle></robndbox></object><object><type>robndbox</type><name>wheat_head</name><pose>Unspecified</pose><truncated>0</truncated><difficult>0</difficult><robndbox><cx>187.0</cx><cy>683.0</cy><w>100.0</w><h>84.0</h><angle>1.570796</angle></robndbox></object><object><type>robndbox</type><name>wheat_head</name><pose>Unspecified</pose><truncated>0</truncated><difficult>0</difficult><robndbox><cx>501.0</cx><cy>344.5</cy><w>86.0</w><h>83.0</h><angle>0.0</angle></robndbox></object><object><type>robndbox</type><name>wheat_head</name><pose>Unspecified</pose><truncated>0</truncated><difficult>0</difficult><robndbox><cx>455.5</cx><cy>974.5</cy><w>59.0</w><h>57.0</h><angle>0.0</angle></robndbox></object><object><type>robndbox</type><name>wheat_head</name><pose>Unspecified</pose><truncated>0</truncated><difficult>0</difficult><robndbox><cx>395.5</cx><cy>1006.0</cy><w>91.0</w><h>36.0</h><angle>0.0</angle></robndbox></object><object><type>robndbox</type><name>wheat_head</name><pose>Unspecified</pose><truncated>0</truncated><difficult>0</difficult><robndbox><cx>361.0</cx><cy>935.5</cy><w>82.0</w><h>67.0</h><angle>0.0</angle></robndbox></object><object><type>robndbox</type><name>wheat_head</name><pose>Unspecified</pose><truncated>0</truncated><difficult>0</difficult><robndbox><cx>279.5</cx><cy>926.5</cy><w>87.0</w><h>83.0</h><angle>1.570796</angle></robndbox></object><object><type>robndbox</type><name>wheat_head</name><pose>Unspecified</pose><truncated>0</truncated><difficult>0</difficult><robndbox><cx>619.5</cx><cy>475.0</cy><w>103.0</w><h>86.0</h><angle>0.0</angle></robndbox></object><object><type>robndbox</type><name>wheat_head</name><pose>Unspecified</pose><truncated>0</truncated><difficult>0</difficult><robndbox><cx>525.5</cx><cy>506.0</cy><w>108.0</w><h>73.0</h><angle>1.570796</angle></robndbox></object><object><type>robndbox</type><name>wheat_head</name><pose>Unspecified</pose><truncated>0</truncated><difficult>0</difficult><robndbox><cx>433.0</cx><cy>527.5</cy><w>99.0</w><h>78.0</h><angle>1.570796</angle></robndbox></object><object><type>robndbox</type><name>wheat_head</name><pose>Unspecified</pose><truncated>0</truncated><difficult>0</difficult><robndbox><cx>297.5</cx><cy>533.0</cy><w>91.0</w><h>76.0</h><angle>0.0</angle></robndbox></object><object><type>robndbox</type><name>wheat_head</name><pose>Unspecified</pose><truncated>0</truncated><difficult>0</difficult><robndbox><cx>259.0</cx><cy>52.5</cy><w>94.0</w><h>49.0</h><angle>0.0</angle></robndbox></object></annotation>