<annotation verified="no">
  <folder>images</folder>
  <filename>crop_0_crop_0_2213-compressed</filename>
  <path>/home/badhon/Documents/thesis/AerialDetection/data/wheat_competition/train/images/crop_0_crop_0_2213-compressed.png</path>
  <source>
    <database>Unknown</database>
  </source>
  <size>
    <width>1024</width>
    <height>1024</height>
    <depth>3</depth>
  </size>
  <segmented>0</segmented>
  <object>
    <type>robndbox</type>
    <name>wheat_head</name>
    <pose>Unspecified</pose>
    <truncated>0</truncated>
    <difficult>0</difficult>
    <robndbox>
      <cx>244.1095</cx>
      <cy>67.0</cy>
      <w>66.7175</w>
      <h>39.973</h>
      <angle>2.368581</angle>
    </robndbox>
  </object>
  <object>
    <type>robndbox</type>
    <name>wheat_head</name>
    <pose>Unspecified</pose>
    <truncated>0</truncated>
    <difficult>0</difficult>
    <robndbox>
      <cx>772.7775</cx>
      <cy>285.9586</cy>
      <w>76.0692</w>
      <h>54.3545</h>
      <angle>0.409924</angle>
    </robndbox>
  </object>
  <object>
    <type>robndbox</type>
    <name>wheat_head</name>
    <pose>Unspecified</pose>
    <truncated>0</truncated>
    <difficult>0</difficult>
    <robndbox>
      <cx>139.809</cx>
      <cy>168.9487</cy>
      <w>82.9664</w>
      <h>48.6222</h>
      <angle>0.063907</angle>
    </robndbox>
  </object>
  <object>
    <type>robndbox</type>
    <name>wheat_head</name>
    <pose>Unspecified</pose>
    <truncated>0</truncated>
    <difficult>0</difficult>
    <robndbox>
      <cx>318.7996</cx>
      <cy>159.3383</cy>
      <w>72.1776</w>
      <h>44.6639</h>
      <angle>2.642258</angle>
    </robndbox>
  </object>
  <object>
    <type>robndbox</type>
    <name>wheat_head</name>
    <pose>Unspecified</pose>
    <truncated>0</truncated>
    <difficult>0</difficult>
    <robndbox>
      <cx>159.7748</cx>
      <cy>84.0619</cy>
      <w>67.8277</w>
      <h>63.6819</h>
      <angle>0.664666</angle>
    </robndbox>
  </object>
  <object>
    <type>robndbox</type>
    <name>wheat_head</name>
    <pose>Unspecified</pose>
    <truncated>0</truncated>
    <difficult>0</difficult>
    <robndbox>
      <cx>888.933</cx>
      <cy>43.2302</cy>
      <w>74.8912</w>
      <h>48.0404</h>
      <angle>1.274851</angle>
    </robndbox>
  </object>
  <object>
    <type>robndbox</type>
    <name>wheat_head</name>
    <pose>Unspecified</pose>
    <truncated>0</truncated>
    <difficult>0</difficult>
    <robndbox>
      <cx>817.8475</cx>
      <cy>180.1726</cy>
      <w>108.7419</w>
      <h>60.1888</h>
      <angle>1.554391</angle>
    </robndbox>
  </object>
  <object>
    <type>robndbox</type>
    <name>wheat_head</name>
    <pose>Unspecified</pose>
    <truncated>0</truncated>
    <difficult>0</difficult>
    <robndbox>
      <cx>93.5</cx>
      <cy>753.7874</cy>
      <w>183.4916</w>
      <h>49.2306</h>
      <angle>2.919876</angle>
    </robndbox>
  </object>
  <object>
    <type>robndbox</type>
    <name>wheat_head</name>
    <pose>Unspecified</pose>
    <truncated>0</truncated>
    <difficult>0</difficult>
    <robndbox>
      <cx>380.886</cx>
      <cy>767.1866</cy>
      <w>179.7848</w>
      <h>48.5706</h>
      <angle>2.98339</angle>
    </robndbox>
  </object>
  <object>
    <type>robndbox</type>
    <name>wheat_head</name>
    <pose>Unspecified</pose>
    <truncated>0</truncated>
    <difficult>0</difficult>
    <robndbox>
      <cx>441.4503</cx>
      <cy>76.6528</cy>
      <w>132.2544</w>
      <h>54.271</h>
      <angle>0.316877</angle>
    </robndbox>
  </object>
  <object>
    <type>robndbox</type>
    <name>wheat_head</name>
    <pose>Unspecified</pose>
    <truncated>0</truncated>
    <difficult>0</difficult>
    <robndbox>
      <cx>409.3012</cx>
      <cy>219.9524</cy>
      <w>73.6983</w>
      <h>59.0484</h>
      <angle>1.168899</angle>
    </robndbox>
  </object>
  <object>
    <type>robndbox</type>
    <name>wheat_head</name>
    <pose>Unspecified</pose>
    <truncated>0</truncated>
    <difficult>0</difficult>
    <robndbox>
      <cx>239.0953</cx>
      <cy>159.0816</cy>
      <w>89.8469</w>
      <h>57.5833</h>
      <angle>0.642087</angle>
    </robndbox>
  </object>
  <object>
    <type>robndbox</type>
    <name>wheat_head</name>
    <pose>Unspecified</pose>
    <truncated>0</truncated>
    <difficult>0</difficult>
    <robndbox>
      <cx>18.2365</cx>
      <cy>365.0</cy>
      <w>80.0168</w>
      <h>67.9334</h>
      <angle>2.022255</angle>
    </robndbox>
  </object>
  <object>
    <type>robndbox</type>
    <name>wheat_head</name>
    <pose>Unspecified</pose>
    <truncated>0</truncated>
    <difficult>0</difficult>
    <robndbox>
      <cx>120.3168</cx>
      <cy>46.9614</cy>
      <w>116.8834</w>
      <h>55.3236</h>
      <angle>0.12892</angle>
    </robndbox>
  </object>
  <object>
    <type>robndbox</type>
    <name>wheat_head</name>
    <pose>Unspecified</pose>
    <truncated>0</truncated>
    <difficult>0</difficult>
    <robndbox>
      <cx>463.4267</cx>
      <cy>846.0767</cy>
      <w>164.8502</w>
      <h>65.4839</h>
      <angle>0.995172</angle>
    </robndbox>
  </object>
  <object>
    <type>robndbox</type>
    <name>wheat_head</name>
    <pose>Unspecified</pose>
    <truncated>0</truncated>
    <difficult>0</difficult>
    <robndbox>
      <cx>972.241</cx>
      <cy>885.3208</cy>
      <w>101.6179</w>
      <h>44.9383</h>
      <angle>1.8137</angle>
    </robndbox>
  </object>
  <object>
    <type>robndbox</type>
    <name>wheat_head</name>
    <pose>Unspecified</pose>
    <truncated>0</truncated>
    <difficult>0</difficult>
    <robndbox>
      <cx>180.0</cx>
      <cy>349.6854</cy>
      <w>131.386</w>
      <h>53.02</h>
      <angle>2.996212</angle>
    </robndbox>
  </object>
  <object>
    <type>robndbox</type>
    <name>wheat_head</name>
    <pose>Unspecified</pose>
    <truncated>0</truncated>
    <difficult>0</difficult>
    <robndbox>
      <cx>81.5</cx>
      <cy>458.9801</cy>
      <w>174.7525</w>
      <h>56.7419</h>
      <angle>0.454653</angle>
    </robndbox>
  </object>
  <object>
    <type>robndbox</type>
    <name>wheat_head</name>
    <pose>Unspecified</pose>
    <truncated>0</truncated>
    <difficult>0</difficult>
    <robndbox>
      <cx>531.158</cx>
      <cy>61.5</cy>
      <w>172.9805</w>
      <h>65.7161</h>
      <angle>0.791009</angle>
    </robndbox>
  </object>
  <object>
    <type>robndbox</type>
    <name>wheat_head</name>
    <pose>Unspecified</pose>
    <truncated>0</truncated>
    <difficult>0</difficult>
    <robndbox>
      <cx>84.6463</cx>
      <cy>561.5031</cy>
      <w>145.9246</w>
      <h>57.096</h>
      <angle>2.595974</angle>
    </robndbox>
  </object>
  <object>
    <type>robndbox</type>
    <name>wheat_head</name>
    <pose>Unspecified</pose>
    <truncated>0</truncated>
    <difficult>0</difficult>
    <robndbox>
      <cx>329.5205</cx>
      <cy>467.0183</cy>
      <w>113.3276</w>
      <h>58.8896</h>
      <angle>1.762282</angle>
    </robndbox>
  </object>
  <object>
    <type>robndbox</type>
    <name>wheat_head</name>
    <pose>Unspecified</pose>
    <truncated>0</truncated>
    <difficult>0</difficult>
    <robndbox>
      <cx>523.831</cx>
      <cy>196.3462</cy>
      <w>132.0387</w>
      <h>65.4288</h>
      <angle>2.154471</angle>
    </robndbox>
  </object>
  <object>
    <type>robndbox</type>
    <name>wheat_head</name>
    <pose>Unspecified</pose>
    <truncated>0</truncated>
    <difficult>0</difficult>
    <robndbox>
      <cx>56.093</cx>
      <cy>154.4795</cy>
      <w>107.8327</w>
      <h>46.2987</h>
      <angle>0.007686</angle>
    </robndbox>
  </object>
  <object>
    <type>robndbox</type>
    <name>wheat_head</name>
    <pose>Unspecified</pose>
    <truncated>0</truncated>
    <difficult>0</difficult>
    <robndbox>
      <cx>41.0</cx>
      <cy>826.031</cy>
      <w>66.6313</w>
      <h>52.723</h>
      <angle>3.003824</angle>
    </robndbox>
  </object>
  <object>
    <type>robndbox</type>
    <name>wheat_head</name>
    <pose>Unspecified</pose>
    <truncated>0</truncated>
    <difficult>0</difficult>
    <robndbox>
      <cx>405.2241</cx>
      <cy>971.287</cy>
      <w>81.2557</w>
      <h>64.0624</h>
      <angle>0.34033</angle>
    </robndbox>
  </object>
  <object>
    <type>robndbox</type>
    <name>wheat_head</name>
    <pose>Unspecified</pose>
    <truncated>0</truncated>
    <difficult>0</difficult>
    <robndbox>
      <cx>649.356</cx>
      <cy>737.1161</cy>
      <w>97.7869</w>
      <h>54.5299</h>
      <angle>2.656221</angle>
    </robndbox>
  </object>
  <object>
    <type>robndbox</type>
    <name>wheat_head</name>
    <pose>Unspecified</pose>
    <truncated>0</truncated>
    <difficult>0</difficult>
    <robndbox>
      <cx>132.5603</cx>
      <cy>262.5606</cy>
      <w>127.5271</w>
      <h>62.3383</h>
      <angle>0.101704</angle>
    </robndbox>
  </object>
  <object>
    <type>robndbox</type>
    <name>wheat_head</name>
    <pose>Unspecified</pose>
    <truncated>0</truncated>
    <difficult>0</difficult>
    <robndbox>
      <cx>893.7336</cx>
      <cy>131.5359</cy>
      <w>77.6539</w>
      <h>49.3168</h>
      <angle>1.234273</angle>
    </robndbox>
  </object>
  <object>
    <type>robndbox</type>
    <name>wheat_head</name>
    <pose>Unspecified</pose>
    <truncated>0</truncated>
    <difficult>0</difficult>
    <robndbox>
      <cx>858.8779</cx>
      <cy>76.8489</cy>
      <w>76.2365</w>
      <h>44.1651</h>
      <angle>1.57422</angle>
    </robndbox>
  </object>
  <object>
    <type>robndbox</type>
    <name>wheat_head</name>
    <pose>Unspecified</pose>
    <truncated>0</truncated>
    <difficult>0</difficult>
    <robndbox>
      <cx>412.5816</cx>
      <cy>868.6983</cy>
      <w>87.5278</w>
      <h>48.8334</h>
      <angle>1.23743</angle>
    </robndbox>
  </object>
  <object>
    <type>robndbox</type>
    <name>wheat_head</name>
    <pose>Unspecified</pose>
    <truncated>0</truncated>
    <difficult>0</difficult>
    <robndbox>
      <cx>167.727</cx>
      <cy>978.9689</cy>
      <w>69.7744</w>
      <h>53.5873</h>
      <angle>2.73944</angle>
    </robndbox>
  </object>
  <object>
    <type>robndbox</type>
    <name>wheat_head</name>
    <pose>Unspecified</pose>
    <truncated>0</truncated>
    <difficult>0</difficult>
    <robndbox>
      <cx>329.8057</cx>
      <cy>985.377</cy>
      <w>73.3047</w>
      <h>63.6689</h>
      <angle>1.539746</angle>
    </robndbox>
  </object>
  <object>
    <type>robndbox</type>
    <name>wheat_head</name>
    <pose>Unspecified</pose>
    <truncated>0</truncated>
    <difficult>0</difficult>
    <robndbox>
      <cx>206.5392</cx>
      <cy>813.5218</cy>
      <w>106.8472</w>
      <h>45.5535</h>
      <angle>2.903265</angle>
    </robndbox>
  </object>
  <object>
    <type>robndbox</type>
    <name>wheat_head</name>
    <pose>Unspecified</pose>
    <truncated>0</truncated>
    <difficult>0</difficult>
    <robndbox>
      <cx>292.4905</cx>
      <cy>614.275</cy>
      <w>78.4466</w>
      <h>38.919</h>
      <angle>2.538227</angle>
    </robndbox>
  </object>
  <object>
    <type>robndbox</type>
    <name>wheat_head</name>
    <pose>Unspecified</pose>
    <truncated>0</truncated>
    <difficult>0</difficult>
    <robndbox>
      <cx>25.9742</cx>
      <cy>656.0002</cy>
      <w>80.015</w>
      <h>51.8191</h>
      <angle>1.572145</angle>
    </robndbox>
  </object>
  <object>
    <type>robndbox</type>
    <name>wheat_head</name>
    <pose>Unspecified</pose>
    <truncated>0</truncated>
    <difficult>0</difficult>
    <robndbox>
      <cx>804.9804</cx>
      <cy>461.7118</cy>
      <w>88.5614</w>
      <h>66.1253</h>
      <angle>2.255924</angle>
    </robndbox>
  </object>
  <object>
    <type>robndbox</type>
    <name>wheat_head</name>
    <pose>Unspecified</pose>
    <truncated>0</truncated>
    <difficult>0</difficult>
    <robndbox>
      <cx>820.9695</cx>
      <cy>471.0</cy>
      <w>46.188</w>
      <h>27.2971</h>
      <angle>1.480534</angle>
    </robndbox>
  </object>
  <object>
    <type>robndbox</type>
    <name>wheat_head</name>
    <pose>Unspecified</pose>
    <truncated>0</truncated>
    <difficult>0</difficult>
    <robndbox>
      <cx>280.6705</cx>
      <cy>227.6064</cy>
      <w>43.3833</w>
      <h>43.949</h>
      <angle>2.194589</angle>
    </robndbox>
  </object>
  <object>
    <type>robndbox</type>
    <name>wheat_head</name>
    <pose>Unspecified</pose>
    <truncated>0</truncated>
    <difficult>0</difficult>
    <robndbox>
      <cx>71.0996</cx>
      <cy>834.0</cy>
      <w>101.5739</w>
      <h>59.8494</h>
      <angle>1.836855</angle>
    </robndbox>
  </object>
</annotation>
