<annotation verified="no">
  <folder>images</folder>
  <filename>crop_0_crop_0_159-compressed</filename>
  <path>/home/badhon/Documents/thesis/AerialDetection/data/wheat_competition/train/images/crop_0_crop_0_159-compressed.png</path>
  <source>
    <database>Unknown</database>
  </source>
  <size>
    <width>1024</width>
    <height>1024</height>
    <depth>3</depth>
  </size>
  <segmented>0</segmented>
  <object>
    <type>robndbox</type>
    <name>wheat_head</name>
    <pose>Unspecified</pose>
    <truncated>0</truncated>
    <difficult>0</difficult>
    <robndbox>
      <cx>935.1512</cx>
      <cy>999.6751</cy>
      <w>45.3178</w>
      <h>44.4113</h>
      <angle>1.601267</angle>
    </robndbox>
  </object>
  <object>
    <type>robndbox</type>
    <name>wheat_head</name>
    <pose>Unspecified</pose>
    <truncated>0</truncated>
    <difficult>0</difficult>
    <robndbox>
      <cx>807.062</cx>
      <cy>305.0315</cy>
      <w>94.0239</w>
      <h>46.7145</h>
      <angle>2.340743</angle>
    </robndbox>
  </object>
  <object>
    <type>robndbox</type>
    <name>wheat_head</name>
    <pose>Unspecified</pose>
    <truncated>0</truncated>
    <difficult>0</difficult>
    <robndbox>
      <cx>991.9408</cx>
      <cy>771.7419</cy>
      <w>70.0268</w>
      <h>62.0974</h>
      <angle>1.593466</angle>
    </robndbox>
  </object>
  <object>
    <type>robndbox</type>
    <name>wheat_head</name>
    <pose>Unspecified</pose>
    <truncated>0</truncated>
    <difficult>0</difficult>
    <robndbox>
      <cx>688.8426</cx>
      <cy>319.3414</cy>
      <w>90.4756</w>
      <h>55.0743</h>
      <angle>0.018378</angle>
    </robndbox>
  </object>
  <object>
    <type>robndbox</type>
    <name>wheat_head</name>
    <pose>Unspecified</pose>
    <truncated>0</truncated>
    <difficult>0</difficult>
    <robndbox>
      <cx>648.6064</cx>
      <cy>262.5426</cy>
      <w>99.3249</w>
      <h>42.1494</h>
      <angle>2.572979</angle>
    </robndbox>
  </object>
  <object>
    <type>robndbox</type>
    <name>wheat_head</name>
    <pose>Unspecified</pose>
    <truncated>0</truncated>
    <difficult>0</difficult>
    <robndbox>
      <cx>318.0818</cx>
      <cy>851.104</cy>
      <w>86.1675</w>
      <h>61.8957</h>
      <angle>0.201336</angle>
    </robndbox>
  </object>
  <object>
    <type>robndbox</type>
    <name>wheat_head</name>
    <pose>Unspecified</pose>
    <truncated>0</truncated>
    <difficult>0</difficult>
    <robndbox>
      <cx>900.9238</cx>
      <cy>202.5824</cy>
      <w>160.3424</w>
      <h>47.7423</h>
      <angle>0.907291</angle>
    </robndbox>
  </object>
  <object>
    <type>robndbox</type>
    <name>wheat_head</name>
    <pose>Unspecified</pose>
    <truncated>0</truncated>
    <difficult>0</difficult>
    <robndbox>
      <cx>407.5</cx>
      <cy>675.9585</cy>
      <w>173.2003</w>
      <h>39.2564</h>
      <angle>2.733834</angle>
    </robndbox>
  </object>
  <object>
    <type>robndbox</type>
    <name>wheat_head</name>
    <pose>Unspecified</pose>
    <truncated>0</truncated>
    <difficult>0</difficult>
    <robndbox>
      <cx>258.6225</cx>
      <cy>660.7115</cy>
      <w>151.75</w>
      <h>45.7581</h>
      <angle>0.92377</angle>
    </robndbox>
  </object>
  <object>
    <type>robndbox</type>
    <name>wheat_head</name>
    <pose>Unspecified</pose>
    <truncated>0</truncated>
    <difficult>0</difficult>
    <robndbox>
      <cx>968.5138</cx>
      <cy>143.5</cy>
      <w>287.0461</w>
      <h>65.1015</h>
      <angle>1.588723</angle>
    </robndbox>
  </object>
  <object>
    <type>robndbox</type>
    <name>wheat_head</name>
    <pose>Unspecified</pose>
    <truncated>0</truncated>
    <difficult>0</difficult>
    <robndbox>
      <cx>449.611</cx>
      <cy>18.2579</cy>
      <w>85.0193</w>
      <h>34.9105</h>
      <angle>0.44394</angle>
    </robndbox>
  </object>
  <object>
    <type>robndbox</type>
    <name>wheat_head</name>
    <pose>Unspecified</pose>
    <truncated>0</truncated>
    <difficult>0</difficult>
    <robndbox>
      <cx>327.0521</cx>
      <cy>77.0</cy>
      <w>157.7443</w>
      <h>44.3934</h>
      <angle>1.789112</angle>
    </robndbox>
  </object>
  <object>
    <type>robndbox</type>
    <name>wheat_head</name>
    <pose>Unspecified</pose>
    <truncated>0</truncated>
    <difficult>0</difficult>
    <robndbox>
      <cx>210.8851</cx>
      <cy>61.4515</cy>
      <w>50.8112</w>
      <h>34.6474</h>
      <angle>0.01056</angle>
    </robndbox>
  </object>
  <object>
    <type>robndbox</type>
    <name>wheat_head</name>
    <pose>Unspecified</pose>
    <truncated>0</truncated>
    <difficult>0</difficult>
    <robndbox>
      <cx>143.4235</cx>
      <cy>17.0599</cy>
      <w>62.9503</w>
      <h>33.3759</h>
      <angle>3.132206</angle>
    </robndbox>
  </object>
  <object>
    <type>robndbox</type>
    <name>wheat_head</name>
    <pose>Unspecified</pose>
    <truncated>0</truncated>
    <difficult>0</difficult>
    <robndbox>
      <cx>294.0718</cx>
      <cy>483.9089</cy>
      <w>80.8259</w>
      <h>32.0369</h>
      <angle>0.078382</angle>
    </robndbox>
  </object>
  <object>
    <type>robndbox</type>
    <name>wheat_head</name>
    <pose>Unspecified</pose>
    <truncated>0</truncated>
    <difficult>0</difficult>
    <robndbox>
      <cx>173.7937</cx>
      <cy>993.5111</cy>
      <w>100.9181</w>
      <h>51.2953</h>
      <angle>2.492793</angle>
    </robndbox>
  </object>
  <object>
    <type>robndbox</type>
    <name>wheat_head</name>
    <pose>Unspecified</pose>
    <truncated>0</truncated>
    <difficult>0</difficult>
    <robndbox>
      <cx>66.7845</cx>
      <cy>993.0213</cy>
      <w>59.4333</w>
      <h>35.5355</h>
      <angle>2.633615</angle>
    </robndbox>
  </object>
  <object>
    <type>robndbox</type>
    <name>wheat_head</name>
    <pose>Unspecified</pose>
    <truncated>0</truncated>
    <difficult>0</difficult>
    <robndbox>
      <cx>815.702</cx>
      <cy>532.121</cy>
      <w>104.0241</w>
      <h>44.8034</h>
      <angle>0.945915</angle>
    </robndbox>
  </object>
  <object>
    <type>robndbox</type>
    <name>wheat_head</name>
    <pose>Unspecified</pose>
    <truncated>0</truncated>
    <difficult>0</difficult>
    <robndbox>
      <cx>807.352</cx>
      <cy>596.0816</cy>
      <w>91.4768</w>
      <h>45.0143</h>
      <angle>1.137938</angle>
    </robndbox>
  </object>
  <object>
    <type>robndbox</type>
    <name>wheat_head</name>
    <pose>Unspecified</pose>
    <truncated>0</truncated>
    <difficult>0</difficult>
    <robndbox>
      <cx>898.1942</cx>
      <cy>545.2719</cy>
      <w>56.2651</w>
      <h>45.3018</h>
      <angle>0.341824</angle>
    </robndbox>
  </object>
  <object>
    <type>robndbox</type>
    <name>wheat_head</name>
    <pose>Unspecified</pose>
    <truncated>0</truncated>
    <difficult>0</difficult>
    <robndbox>
      <cx>962.0133</cx>
      <cy>665.1787</cy>
      <w>58.0044</w>
      <h>61.702</h>
      <angle>2.121997</angle>
    </robndbox>
  </object>
  <object>
    <type>robndbox</type>
    <name>wheat_head</name>
    <pose>Unspecified</pose>
    <truncated>0</truncated>
    <difficult>0</difficult>
    <robndbox>
      <cx>767.4264</cx>
      <cy>715.291</cy>
      <w>55.806</w>
      <h>37.4397</h>
      <angle>3.038588</angle>
    </robndbox>
  </object>
  <object>
    <type>robndbox</type>
    <name>wheat_head</name>
    <pose>Unspecified</pose>
    <truncated>0</truncated>
    <difficult>0</difficult>
    <robndbox>
      <cx>908.8686</cx>
      <cy>757.4587</cy>
      <w>72.6176</w>
      <h>45.2995</h>
      <angle>0.913865</angle>
    </robndbox>
  </object>
  <object>
    <type>robndbox</type>
    <name>wheat_head</name>
    <pose>Unspecified</pose>
    <truncated>0</truncated>
    <difficult>0</difficult>
    <robndbox>
      <cx>811.6759</cx>
      <cy>886.9112</cy>
      <w>90.1597</w>
      <h>52.4546</h>
      <angle>1.918713</angle>
    </robndbox>
  </object>
  <object>
    <type>robndbox</type>
    <name>wheat_head</name>
    <pose>Unspecified</pose>
    <truncated>0</truncated>
    <difficult>0</difficult>
    <robndbox>
      <cx>884.8644</cx>
      <cy>880.1357</cy>
      <w>56.8743</w>
      <h>43.3579</h>
      <angle>0.653962</angle>
    </robndbox>
  </object>
  <object>
    <type>robndbox</type>
    <name>wheat_head</name>
    <pose>Unspecified</pose>
    <truncated>0</truncated>
    <difficult>0</difficult>
    <robndbox>
      <cx>850.0669</cx>
      <cy>979.3604</cy>
      <w>80.0253</w>
      <h>55.889</h>
      <angle>1.546409</angle>
    </robndbox>
  </object>
  <object>
    <type>robndbox</type>
    <name>wheat_head</name>
    <pose>Unspecified</pose>
    <truncated>0</truncated>
    <difficult>0</difficult>
    <robndbox>
      <cx>916.5998</cx>
      <cy>212.255</cy>
      <w>183.5542</w>
      <h>47.691</h>
      <angle>1.643993</angle>
    </robndbox>
  </object>
  <object>
    <type>robndbox</type>
    <name>wheat_head</name>
    <pose>Unspecified</pose>
    <truncated>0</truncated>
    <difficult>0</difficult>
    <robndbox>
      <cx>854.8751</cx>
      <cy>354.1004</cy>
      <w>94.7462</w>
      <h>50.8894</h>
      <angle>0.568327</angle>
    </robndbox>
  </object>
  <object>
    <type>robndbox</type>
    <name>wheat_head</name>
    <pose>Unspecified</pose>
    <truncated>0</truncated>
    <difficult>0</difficult>
    <robndbox>
      <cx>45.0</cx>
      <cy>788.4172</cy>
      <w>52.2308</w>
      <h>35.1376</h>
      <angle>0.045263</angle>
    </robndbox>
  </object>
  <object>
    <type>robndbox</type>
    <name>wheat_head</name>
    <pose>Unspecified</pose>
    <truncated>0</truncated>
    <difficult>0</difficult>
    <robndbox>
      <cx>49.355</cx>
      <cy>827.3632</cy>
      <w>59.2431</w>
      <h>31.0958</h>
      <angle>1.686968</angle>
    </robndbox>
  </object>
</annotation>
