<annotation verified="no">
  <folder>images</folder>
  <filename>crop_1_crop_0_2999-compressed</filename>
  <path>/home/badhon/Documents/thesis/AerialDetection/data/wheat_competition/train/images/crop_1_crop_0_2999-compressed.png</path>
  <source>
    <database>Unknown</database>
  </source>
  <size>
    <width>1024</width>
    <height>1024</height>
    <depth>3</depth>
  </size>
  <segmented>0</segmented>
  <object>
    <type>robndbox</type>
    <name>wheat_head</name>
    <pose>Unspecified</pose>
    <truncated>0</truncated>
    <difficult>0</difficult>
    <robndbox>
      <cx>329.5868</cx>
      <cy>336.0843</cy>
      <w>131.9758</w>
      <h>60.4663</h>
      <angle>0.13694</angle>
    </robndbox>
  </object>
  <object>
    <type>robndbox</type>
    <name>wheat_head</name>
    <pose>Unspecified</pose>
    <truncated>0</truncated>
    <difficult>0</difficult>
    <robndbox>
      <cx>601.6321</cx>
      <cy>954.3212</cy>
      <w>128.2125</w>
      <h>51.3336</h>
      <angle>1.847395</angle>
    </robndbox>
  </object>
  <object>
    <type>robndbox</type>
    <name>wheat_head</name>
    <pose>Unspecified</pose>
    <truncated>0</truncated>
    <difficult>0</difficult>
    <robndbox>
      <cx>603.2707</cx>
      <cy>230.2144</cy>
      <w>113.6266</w>
      <h>39.5596</h>
      <angle>2.042282</angle>
    </robndbox>
  </object>
  <object>
    <type>robndbox</type>
    <name>wheat_head</name>
    <pose>Unspecified</pose>
    <truncated>0</truncated>
    <difficult>0</difficult>
    <robndbox>
      <cx>687.6676</cx>
      <cy>23.4805</cy>
      <w>71.0632</w>
      <h>43.4075</h>
      <angle>2.419663</angle>
    </robndbox>
  </object>
  <object>
    <type>robndbox</type>
    <name>wheat_head</name>
    <pose>Unspecified</pose>
    <truncated>0</truncated>
    <difficult>0</difficult>
    <robndbox>
      <cx>651.5223</cx>
      <cy>129.3387</cy>
      <w>99.4721</w>
      <h>72.6677</h>
      <angle>1.624197</angle>
    </robndbox>
  </object>
  <object>
    <type>robndbox</type>
    <name>wheat_head</name>
    <pose>Unspecified</pose>
    <truncated>0</truncated>
    <difficult>0</difficult>
    <robndbox>
      <cx>133.7414</cx>
      <cy>290.1722</cy>
      <w>260.2599</w>
      <h>72.3562</h>
      <angle>0.131032</angle>
    </robndbox>
  </object>
  <object>
    <type>robndbox</type>
    <name>wheat_head</name>
    <pose>Unspecified</pose>
    <truncated>0</truncated>
    <difficult>0</difficult>
    <robndbox>
      <cx>536.1982</cx>
      <cy>56.0</cy>
      <w>140.0905</w>
      <h>57.7842</h>
      <angle>0.90303</angle>
    </robndbox>
  </object>
  <object>
    <type>robndbox</type>
    <name>wheat_head</name>
    <pose>Unspecified</pose>
    <truncated>0</truncated>
    <difficult>0</difficult>
    <robndbox>
      <cx>645.0</cx>
      <cy>33.8088</cy>
      <w>67.074</w>
      <h>45.5197</h>
      <angle>1.582848</angle>
    </robndbox>
  </object>
</annotation>
